LICENSE
README.md
__init__.py
wandb_carbs.py
wandb_carbs-0.0.8.dist-info/LICENSE
wandb_carbs-0.0.8.dist-info/METADATA
wandb_carbs-0.0.8.dist-info/WHEEL
wandb_carbs-0.0.8.dist-info/RECORD
